secretscli/__init__.py
secretscli/api/client.py
secretscli/auth.py
secretscli/cli.py
secretscli/commands/__init__.py
secretscli/commands/project.py
secretscli/commands/secrets.py
secretscli/commands/workspace.py
secretscli/config.py
secretscli/encryption.py
secretscli/prompts.py
secretscli/utils/credentials.py
secretscli/utils/decorators.py
secretscli/utils/diff.py
secretscli/utils/env_manager.py
secretscli/utils/utils.py
secretscli/utils/validators.py
secretscli_py-1.0.1.dist-info/METADATA
secretscli_py-1.0.1.dist-info/WHEEL
secretscli_py-1.0.1.dist-info/entry_points.txt
secretscli_py-1.0.1.dist-info/licenses/LICENSE
secretscli_py-1.0.1.dist-info/RECORD
