Metadata-Version: 2.4
Name: secretscli-py
Version: 1.0.1
Summary: SecretsCLI is a lightweight command-line interface tool for securely managing and retrieving your secrets across devices. With an intuitive login system, it ensures your sensitive information such as API keys, passwords, and other private data remains protected while being easily accessible from any environment. Designed for simplicity and security, SecretsCLI allows seamless integration with your development workflow.
License: MIT
License-File: LICENSE
Author: The Seventeen
Author-email: hello@theseventeen.co
Requires-Python: >=3.12
Classifier: License :: OSI Approved :: MIT License
Classifier: Programming Language :: Python :: 3
Classifier: Programming Language :: Python :: 3.12
Classifier: Programming Language :: Python :: 3.13
Classifier: Programming Language :: Python :: 3.14
Requires-Dist: cryptography (>=46.0.3,<47.0.0)
Requires-Dist: email-validator (>=2.3.0,<3.0.0)
Requires-Dist: keyring (>=25.7.0,<26.0.0)
Requires-Dist: keyrings-alt (>=5.0.2,<6.0.0)
Requires-Dist: pynacl (>=1.6.2,<2.0.0)
Requires-Dist: questionary (>=2.1.1,<3.0.0)
Requires-Dist: requests (>=2.32.5,<3.0.0)
Requires-Dist: secretstorage (>=3.5.0,<4.0.0)
Requires-Dist: typer (>=0.20.0,<0.21.0)
